hebo/__init__.py
hebo/cli.py
hebo/config.py
hebo/utils.py
hebo_cli-0.1.8.dist-info/METADATA
hebo_cli-0.1.8.dist-info/WHEEL
hebo_cli-0.1.8.dist-info/entry_points.txt
hebo_cli-0.1.8.dist-info/licenses/LICENSE.md
hebo_cli-0.1.8.dist-info/RECORD
